{
  "Media": {
    "id": -2,
    "name": "Medium",
    "subpages": false,
    "content": false,
    "aliases": [],
    "issubject": true,
    "istalk": false
  },
  "Special": {
    "id": -1,
    "name": "Spezial",
    "subpages": false,
    "content": false,
    "aliases": [],
    "issubject": true,
    "istalk": false
  },
  "Main": {
    "id": 0,
    "name": "Main",
    "subpages": false,
    "content": true,
    "aliases": [],
    "issubject": true,
    "istalk": false
  },
  "Talk": {
    "id": 1,
    "name": "Diskussion",
    "subpages": true,
    "content": false,
    "aliases": [],
    "issubject": false,
    "istalk": true
  },
  "User": {
    "id": 2,
    "name": "Benutzer",
    "subpages": true,
    "content": false,
    "aliases": [
      "Benutzerin"
    ],
    "issubject": true,
    "istalk": false
  },
  "User talk": {
    "id": 3,
    "name": "Benutzer Diskussion",
    "subpages": true,
    "content": false,
    "aliases": [
      "BD",
      "Benutzerin Diskussion"
    ],
    "issubject": false,
    "istalk": true
  },
  "Project": {
    "id": 4,
    "name": "Wiktionary",
    "subpages": true,
    "content": false,
    "aliases": [
      "WT"
    ],
    "issubject": true,
    "istalk": false
  },
  "Project talk": {
    "id": 5,
    "name": "Wiktionary Diskussion",
    "subpages": true,
    "content": false,
    "aliases": [
      "Wiktionary talk"
    ],
    "issubject": false,
    "istalk": true
  },
  "File": {
    "id": 6,
    "name": "Datei",
    "subpages": false,
    "content": false,
    "aliases": [
      "Bild",
      "Image"
    ],
    "issubject": true,
    "istalk": false
  },
  "File talk": {
    "id": 7,
    "name": "Datei Diskussion",
    "subpages": true,
    "content": false,
    "aliases": [
      "Bild Diskussion",
      "Image talk"
    ],
    "issubject": false,
    "istalk": true
  },
  "MediaWiki": {
    "id": 8,
    "name": "MediaWiki",
    "subpages": true,
    "content": false,
    "aliases": [],
    "issubject": true,
    "istalk": false
  },
  "MediaWiki talk": {
    "id": 9,
    "name": "MediaWiki Diskussion",
    "subpages": true,
    "content": false,
    "aliases": [],
    "issubject": false,
    "istalk": true
  },
  "Template": {
    "id": 10,
    "name": "Vorlage",
    "subpages": true,
    "content": false,
    "aliases": [],
    "issubject": true,
    "istalk": false
  },
  "Template talk": {
    "id": 11,
    "name": "Vorlage Diskussion",
    "subpages": true,
    "content": false,
    "aliases": [],
    "issubject": false,
    "istalk": true
  },
  "Help": {
    "id": 12,
    "name": "Hilfe",
    "subpages": true,
    "content": false,
    "aliases": [],
    "issubject": true,
    "istalk": false
  },
  "Help talk": {
    "id": 13,
    "name": "Hilfe Diskussion",
    "subpages": true,
    "content": false,
    "aliases": [],
    "issubject": false,
    "istalk": true
  },
  "Category": {
    "id": 14,
    "name": "Kategorie",
    "subpages": false,
    "content": false,
    "aliases": [],
    "issubject": true,
    "istalk": false
  },
  "Category talk": {
    "id": 15,
    "name": "Kategorie Diskussion",
    "subpages": true,
    "content": false,
    "aliases": [],
    "issubject": false,
    "istalk": true
  },
  "Verzeichnis": {
    "id": 102,
    "name": "Verzeichnis",
    "subpages": true,
    "content": false,
    "aliases": [],
    "issubject": true,
    "istalk": false
  },
  "Verzeichnis Diskussion": {
    "id": 103,
    "name": "Verzeichnis Diskussion",
    "subpages": true,
    "content": false,
    "aliases": [],
    "issubject": false,
    "istalk": true
  },
  "Thesaurus": {
    "id": 104,
    "name": "Thesaurus",
    "subpages": true,
    "content": false,
    "aliases": [
      "WikiSaurus"
    ],
    "issubject": true,
    "istalk": false
  },
  "Thesaurus talk": {
    "id": 105,
    "name": "Thesaurus Diskussion",
    "subpages": true,
    "content": false,
    "aliases": [
      "WikiSaurus Diskussion"
    ],
    "issubject": false,
    "istalk": true
  },
  "Rhymes": {
    "id": 106,
    "name": "Reim",
    "subpages": true,
    "content": false,
    "aliases": [],
    "issubject": true,
    "istalk": false
  },
  "Rhymes talk": {
    "id": 107,
    "name": "Reim Diskussion",
    "subpages": true,
    "content": false,
    "aliases": [],
    "issubject": false,
    "istalk": true
  },
  "Flexion": {
    "id": 108,
    "name": "Flexion",
    "subpages": true,
    "content": false,
    "aliases": [],
    "issubject": true,
    "istalk": false
  },
  "Flexion Diskussion": {
    "id": 109,
    "name": "Flexion Diskussion",
    "subpages": true,
    "content": false,
    "aliases": [],
    "issubject": false,
    "istalk": true
  },
  "Reconstruction": {
    "id": 110,
    "name": "Rekonstruktion",
    "subpages": true,
    "content": false,
    "aliases": [],
    "issubject": true,
    "istalk": false
  },
  "Reconstruction talk": {
    "id": 111,
    "name": "Rekonstruktion Diskussion",
    "subpages": true,
    "content": false,
    "aliases": [],
    "issubject": false,
    "istalk": true
  },
  "TimedText": {
    "id": 710,
    "name": "TimedText",
    "subpages": false,
    "content": false,
    "aliases": [],
    "issubject": true,
    "istalk": false
  },
  "TimedText talk": {
    "id": 711,
    "name": "TimedText talk",
    "subpages": false,
    "content": false,
    "aliases": [],
    "issubject": false,
    "istalk": true
  },
  "Module": {
    "id": 828,
    "name": "Modul",
    "subpages": true,
    "content": false,
    "aliases": [],
    "issubject": true,
    "istalk": false
  },
  "Module talk": {
    "id": 829,
    "name": "Modul Diskussion",
    "subpages": true,
    "content": false,
    "aliases": [],
    "issubject": false,
    "istalk": true
  }
}
